iarm/__init__.py
iarm/arm.py
iarm/cpu.py
iarm/exceptions.py
iarm/arm_instructions/__init__.py
iarm/arm_instructions/_meta.py
iarm/arm_instructions/arithmetic.py
iarm/arm_instructions/conditional_branch.py
iarm/arm_instructions/data_movement.py
iarm/arm_instructions/directives.py
iarm/arm_instructions/logic.py
iarm/arm_instructions/memory.py
iarm/arm_instructions/misc.py
iarm/arm_instructions/shift.py
iarm/arm_instructions/unconditional_branch.py
iarm-0.1.0.dist-info/DESCRIPTION.rst
iarm-0.1.0.dist-info/METADATA
iarm-0.1.0.dist-info/RECORD
iarm-0.1.0.dist-info/WHEEL
iarm-0.1.0.dist-info/metadata.json
iarm-0.1.0.dist-info/top_level.txt
iarm-0.1.0.dist-info/zip-safe
iarm_kernel/__init__.py
iarm_kernel/iarmkernel.py
iarm_kernel/install.py
