Metadata-Version: 1.0
Name: iarm
Version: 0.1.0
Summary: An interpreter for the ARM instruction set and an accompanying Jupyter kernel
Home-page: https://github.com/DeepHorizons/iarm
Author: Joshua Milas
Author-email: josh.milas@gmail.com
License: MIT
Platform: UNKNOWN
